niceguicrud/__init__.py
niceguicrud/basemodel_to_table.py
niceguicrud/nicecrud.py
niceguicrud/show_error.py
niceguicrud/input_handlers/__init__.py
niceguicrud/input_handlers/base.py
niceguicrud/input_handlers/boolean.py
niceguicrud/input_handlers/collections.py
niceguicrud/input_handlers/nested.py
niceguicrud/input_handlers/numeric.py
niceguicrud/input_handlers/selection.py
niceguicrud/input_handlers/string.py
niceguicrud/input_handlers/temporal.py
niceguicrud-0.1.11.dist-info/METADATA
niceguicrud-0.1.11.dist-info/WHEEL
niceguicrud-0.1.11.dist-info/licenses/LICENSE
niceguicrud-0.1.11.dist-info/RECORD
