Metadata-Version: 2.4
Name: niceguicrud
Version: 0.1.11
Summary: Edit your pydantic models with a nice GUI - CRUD Create Update Replace Delete
Author-email: Dronakurl <tbo73oij5@mozmail.com>
License-Expression: MIT
License-File: LICENSE
Classifier: Programming Language :: Python :: 3
Classifier: Programming Language :: Python :: 3.12
Classifier: Programming Language :: Python :: 3.13
Requires-Python: >=3.12
Requires-Dist: nicegui>=3.0.0
Requires-Dist: pydantic>=2.8.0
